bospy/__init__.py
bospy/bos.py
bospy/common_pb2.py
bospy/common_pb2.pyi
bospy/common_pb2_grpc.py
bospy/run.py
bospy/run_test.py
bospy/utils.py
bospy-0.0.18.dist-info/METADATA
bospy-0.0.18.dist-info/WHEEL
bospy-0.0.18.dist-info/RECORD
