Metadata-Version: 2.4
Name: bospy
Version: 0.0.18
Summary: a package for accessing bos resources.
Project-URL: Homepage, https://github.com/jamesryancoleman/bospy
Project-URL: Issues, https://github.com/jamesryancoleman/bospy/issues
Author-email: James Coleman <jamesryancoleman@gmail.com>
Classifier: License :: OSI Approved :: MIT License
Classifier: Operating System :: OS Independent
Classifier: Programming Language :: Python :: 3
Requires-Python: >=3.8
